curve2mesh/__init__.py
curve2mesh/curve2mesh.py
curve2mesh-0.1.4.dist-info/LICENSE
curve2mesh-0.1.4.dist-info/METADATA
curve2mesh-0.1.4.dist-info/WHEEL
curve2mesh-0.1.4.dist-info/RECORD
