Metadata-Version: 2.1
Name: curve2mesh
Version: 0.1.4
Summary: Python library to create 3D mesh from a 2D curve by revolving.
License: MIT
Author: Chaitanya Kesanapalli
Author-email: 7126460+ckesanapalli@users.noreply.github.com
Requires-Python: >=3.7,<4.0
Classifier: License :: OSI Approved :: MIT License
Classifier: Programming Language :: Python :: 3
Classifier: Programming Language :: Python :: 3.7
Classifier: Programming Language :: Python :: 3.8
Classifier: Programming Language :: Python :: 3.9
Classifier: Programming Language :: Python :: 3.10
Classifier: Programming Language :: Python :: 3.11
Classifier: Programming Language :: Python :: 3.12
